{ "height":24,
 "infinite":false,
 "layers":[
        {
         "data":[22, 22, 22, 22, 22, 22, 22, 22, 22, 22, 22, 22, 22, 22, 22, 22, 22, 22, 22, 22, 22, 22, 22, 22, 22, 22, 22, 22, 22, 22, 22, 22, 22, 22, 22, 22, 22, 22, 22, 22, 22, 22, 22, 22, 22, 22, 22, 22, 22, 22, 22, 22, 22, 22, 22, 22, 22, 22, 22, 22, 22, 22, 22, 22, 22, 22, 22, 22, 22, 22, 22, 22, 22, 22, 22, 22, 22, 22, 22, 22, 22, 22, 22, 22, 22, 22, 22, 22, 22, 22, 22, 22, 22, 22, 22, 22, 22, 22, 22, 22, 22, 22, 22, 22, 22, 22, 22, 22, 22, 22, 22, 22, 22, 22, 22, 22, 22, 22, 22, 22, 22, 22, 22, 22, 22, 22, 22, 22, 22, 22, 22, 22, 22, 22, 22, 22, 22, 22, 22, 22, 22, 22, 22, 22, 22, 22, 22, 22, 22, 22, 22, 22, 22, 22, 22, 22, 22, 22, 22, 22, 22, 22, 22, 22, 22, 22, 22, 22, 22, 22, 22, 22, 22, 22, 22, 22, 22, 22, 22, 22, 22, 22, 22, 22, 22, 22, 22, 22, 22, 22, 22, 22, 22, 22, 22, 22, 22, 22, 22, 22, 22, 22, 22, 22, 22, 22, 22, 22, 22, 22, 22, 22, 22, 22, 22, 22, 22, 22, 22, 22, 22, 22, 22, 22, 22, 22, 22, 22, 22, 22, 22, 22, 22, 22, 22, 22, 22, 22, 22, 22, 22, 22, 22, 22, 22, 22, 22, 22, 22, 22, 22, 22, 22, 22, 22, 22, 22, 22, 22, 22, 22, 22, 22, 22, 22, 22, 22, 22, 22, 22, 22, 22, 22, 22, 22, 22, 22, 22, 22, 22, 22, 22, 22, 22, 22, 22, 22, 22, 22, 22, 22, 22, 22, 22, 22, 22, 22, 22, 22, 22, 22, 22, 22, 22, 22, 22, 22, 22, 22, 22, 22, 22, 22, 22, 22, 22, 22, 22, 22, 22, 22, 22, 22, 22, 22, 22, 22, 22, 22, 22, 22, 22, 22, 22, 22, 22, 22, 22, 22, 22, 22, 22, 22, 22, 22, 22, 22, 22, 22, 22, 22, 22, 22, 22, 22, 22, 22, 22, 22, 22, 22, 22, 22, 22, 22, 22, 22, 22, 22, 22, 22, 22, 22, 22, 22, 22, 22, 22, 22, 22, 22, 22, 22, 22, 22, 22, 22, 22, 22, 22, 22, 22, 22, 22, 22, 22, 22, 22, 22, 22, 22, 22, 22, 22, 22, 22, 22, 22, 22, 22, 22, 22, 22, 22, 22, 22, 22, 22, 22, 22, 22, 22, 22, 22, 22, 22, 22, 22, 22, 22, 22, 22, 22, 22, 22, 22, 22, 22, 22, 22, 22, 22, 22, 22, 22, 22, 22, 22, 22, 22, 22, 22, 22, 22, 22, 22, 22, 22, 22, 22, 22, 22, 22, 22, 22, 22, 22, 22, 22, 22, 22, 22, 22, 22, 22, 22, 22, 22, 22, 22, 22, 22, 22, 22, 22, 22, 22, 22, 22, 22, 22, 22, 22, 22, 22, 22, 22, 22, 22, 22, 22, 22, 22, 22, 22, 22, 22, 22, 22, 22, 22, 22, 22, 22, 22, 22, 22, 22, 22, 22, 22, 22, 22, 22, 22, 22, 22, 22, 22, 22, 22, 22, 22, 22, 22, 22, 22, 22, 22, 22, 22, 22, 22, 22, 22, 22, 22, 22, 22, 22, 22, 22, 22, 22, 22, 22, 22, 22, 22, 22, 22, 22, 22, 22, 22, 22, 22, 22, 22, 22, 22, 22, 22, 22, 22, 22],
         "height":24,
         "id":1,
         "name":"Background",
         "opacity":1,
         "type":"tilelayer",
         "visible":true,
         "width":24,
         "x":0,
         "y":0
        }, 
        {
         "data":[52, 52, 52, 52, 52, 52, 52, 52, 52, 52, 52, 52, 52, 52, 52, 52, 52, 52, 52, 52, 52, 52, 52, 52, 31, 0, 0, 0, 0, 0, 0, 0, 0, 0, 0, 0, 0, 0, 0, 0, 0, 0, 0, 0, 0, 0, 0, 33, 31, 0, 0, 0, 0, 0, 0, 0, 0, 0, 0, 0, 0, 0, 0, 0, 0, 0, 0, 0, 0, 0, 0, 33, 31, 0, 0, 0, 0, 0, 0, 0, 0, 0, 0, 0, 0, 0, 0, 0, 0, 0, 0, 0, 0, 0, 0, 33, 31, 0, 0, 0, 0, 0, 0, 0, 0, 0, 0, 0, 0, 0, 0, 0, 0, 0, 0, 0, 0, 0, 0, 33, 31, 0, 0, 0, 0, 0, 0, 0, 0, 0, 0, 0, 0, 0, 0, 0, 0, 0, 0, 0, 0, 0, 0, 33, 31, 0, 0, 0, 0, 0, 0, 0, 0, 0, 0, 0, 0, 0, 0, 0, 0, 0, 0, 0, 0, 0, 0, 33, 31, 0, 0, 0, 0, 0, 0, 0, 0, 0, 0, 0, 0, 0, 0, 0, 0, 0, 0, 0, 0, 0, 0, 33, 31, 0, 0, 0, 0, 0, 0, 0, 0, 0, 0, 0, 0, 0, 0, 0, 0, 0, 0, 0, 0, 0, 0, 33, 31, 0, 0, 0, 0, 0, 0, 0, 0, 0, 0, 0, 0, 0, 0, 0, 0, 0, 0, 0, 0, 0, 0, 33, 31, 0, 0, 0, 0, 0, 0, 0, 0, 0, 0, 0, 0, 0, 0, 0, 0, 0, 0, 0, 0, 0, 0, 33, 31, 0, 0, 0, 0, 0, 0, 0, 0, 0, 0, 0, 0, 0, 0, 0, 0, 0, 0, 0, 0, 0, 0, 33, 31, 0, 0, 0, 0, 0, 0, 0, 0, 0, 0, 0, 0, 0, 0, 0, 0, 0, 0, 0, 0, 0, 0, 33, 31, 0, 0, 203, 204, 203, 204, 0, 0, 0, 0, 0, 0, 0, 0, 0, 0, 0, 0, 0, 0, 0, 0, 33, 31, 0, 0, 223, 224, 223, 224, 0, 0, 0, 0, 0, 0, 0, 0, 0, 0, 0, 0, 0, 0, 0, 0, 33, 31, 0, 0, 203, 0, 0, 0, 0, 0, 0, 0, 0, 0, 0, 0, 0, 0, 0, 0, 0, 0, 0, 0, 33, 31, 0, 0, 223, 0, 0, 0, 0, 0, 0, 0, 0, 0, 0, 0, 0, 0, 0, 0, 0, 0, 0, 0, 33, 31, 0, 0, 203, 0, 0, 0, 0, 0, 0, 0, 0, 0, 0, 0, 0, 0, 0, 0, 0, 0, 0, 0, 33, 31, 0, 0, 223, 0, 0, 0, 0, 0, 0, 0, 0, 0, 0, 0, 0, 0, 0, 0, 0, 0, 0, 0, 33, 31, 0, 0, 203, 204, 203, 204, 203, 204, 203, 204, 203, 0, 0, 203, 204, 203, 204, 203, 204, 203, 0, 0, 33, 31, 0, 0, 223, 224, 223, 224, 223, 224, 223, 224, 223, 0, 0, 223, 224, 223, 224, 223, 224, 223, 0, 0, 33, 31, 0, 0, 0, 0, 0, 0, 0, 0, 0, 0, 0, 0, 0, 0, 0, 0, 0, 0, 0, 0, 0, 0, 33, 31, 0, 0, 0, 0, 0, 0, 0, 0, 0, 0, 0, 0, 0, 0, 0, 0, 0, 0, 0, 0, 0, 0, 33, 51, 52, 52, 52, 52, 52, 52, 52, 52, 52, 52, 52, 52, 52, 52, 52, 52, 52, 52, 52, 52, 52, 52, 53],
         "height":24,
         "id":3,
         "name":"Blocked",
         "opacity":1,
         "type":"tilelayer",
         "visible":true,
         "width":24,
         "x":0,
         "y":0
        }, 
        {
         "draworder":"topdown",
         "id":2,
         "name":"Coins",
         "objects":[
                {
                 "height":0,
                 "id":4,
                 "name":"coin",
                 "point":true,
                 "rotation":0,
                 "type":"coin",
                 "visible":true,
                 "width":0,
                 "x":1214,
                 "y":348
                }, 
                {
                 "height":0,
                 "id":5,
                 "name":"coin",
                 "point":true,
                 "rotation":0,
                 "type":"coin",
                 "visible":true,
                 "width":0,
                 "x":822,
                 "y":824
                }, 
                {
                 "height":0,
                 "id":6,
                 "name":"coin",
                 "point":true,
                 "rotation":0,
                 "type":"coin",
                 "visible":true,
                 "width":0,
                 "x":1276,
                 "y":896
                }, 
                {
                 "height":0,
                 "id":7,
                 "name":"coin",
                 "point":true,
                 "rotation":0,
                 "type":"coin",
                 "visible":true,
                 "width":0,
                 "x":266,
                 "y":526
                }, 
                {
                 "height":0,
                 "id":8,
                 "name":"coin",
                 "point":true,
                 "rotation":0,
                 "type":"coin",
                 "visible":true,
                 "width":0,
                 "x":1136,
                 "y":206
                }, 
                {
                 "height":0,
                 "id":9,
                 "name":"coin",
                 "point":true,
                 "rotation":0,
                 "type":"coin",
                 "visible":true,
                 "width":0,
                 "x":1156,
                 "y":702
                }, 
                {
                 "height":0,
                 "id":18,
                 "name":"coin",
                 "point":true,
                 "rotation":0,
                 "type":"coin",
                 "visible":true,
                 "width":0,
                 "x":320,
                 "y":1438
                }],
         "opacity":1,
         "type":"objectgroup",
         "visible":true,
         "x":0,
         "y":0
        }, 
        {
         "draworder":"topdown",
         "id":4,
         "name":"Portal",
         "objects":[
                {
                 "height":0,
                 "id":3,
                 "name":"portal",
                 "point":true,
                 "rotation":0,
                 "type":"portal",
                 "visible":true,
                 "width":0,
                 "x":676,
                 "y":62
                }],
         "opacity":1,
         "type":"objectgroup",
         "visible":true,
         "x":0,
         "y":0
        }, 
        {
         "draworder":"topdown",
         "id":5,
         "name":"Enemies",
         "objects":[
                {
                 "height":0,
                 "id":1,
                 "name":"enemy",
                 "point":true,
                 "rotation":0,
                 "type":"enemy",
                 "visible":true,
                 "width":0,
                 "x":660,
                 "y":370
                }, 
                {
                 "height":0,
                 "id":12,
                 "name":"enemy",
                 "point":true,
                 "rotation":0,
                 "type":"enemy",
                 "visible":true,
                 "width":0,
                 "x":662,
                 "y":494
                }, 
                {
                 "height":0,
                 "id":13,
                 "name":"enemy",
                 "point":true,
                 "rotation":0,
                 "type":"enemy",
                 "visible":true,
                 "width":0,
                 "x":538,
                 "y":632
                }, 
                {
                 "height":0,
                 "id":14,
                 "name":"enemy",
                 "point":true,
                 "rotation":0,
                 "type":"enemy",
                 "visible":true,
                 "width":0,
                 "x":370,
                 "y":318
                }, 
                {
                 "height":0,
                 "id":15,
                 "name":"enemy",
                 "point":true,
                 "rotation":0,
                 "type":"enemy",
                 "visible":true,
                 "width":0,
                 "x":1146,
                 "y":1132
                }, 
                {
                 "height":0,
                 "id":17,
                 "name":"enemy",
                 "point":true,
                 "rotation":0,
                 "type":"enemy",
                 "visible":true,
                 "width":0,
                 "x":130,
                 "y":1270
                }],
         "opacity":1,
         "type":"objectgroup",
         "visible":true,
         "x":0,
         "y":0
        }, 
        {
         "draworder":"topdown",
         "id":6,
         "name":"Player",
         "objects":[
                {
                 "height":0,
                 "id":2,
                 "name":"startingPosition",
                 "point":true,
                 "rotation":0,
                 "type":"startingPosition",
                 "visible":true,
                 "width":0,
                 "x":136,
                 "y":1418
                }, 
                {
                 "height":0,
                 "id":16,
                 "name":"startingPositionPortal",
                 "point":true,
                 "rotation":0,
                 "type":"startingPositionPortal",
                 "visible":true,
                 "width":0,
                 "x":680,
                 "y":144
                }],
         "opacity":1,
         "type":"objectgroup",
         "visible":true,
         "x":0,
         "y":0
        }],
 "nextlayerid":7,
 "nextobjectid":19,
 "orientation":"orthogonal",
 "renderorder":"right-down",
 "tiledversion":"1.2.4",
 "tileheight":64,
 "tilesets":[
        {
         "columns":20,
         "firstgid":1,
         "image":"..\/..\/..\/05 - Top Down RPG\/01_Creating a Level in Tiled\/project_start\/RPGpack_sheet.png",
         "imageheight":832,
         "imagewidth":1280,
         "margin":0,
         "name":"RPGpack_sheet",
         "spacing":0,
         "tilecount":260,
         "tileheight":64,
         "tilewidth":64
        }],
 "tilewidth":64,
 "type":"map",
 "version":1.2,
 "width":24
}